{
  "articles": [
    {
      "title": "近況報告　2月4日～5日",
      "url": "https://ameblo.jp/luidasbar/entry-12956671294.html",
      "content": "<p>歡迎光臨魯伊達酒吧<img alt=\"生ビール\" class=\"emoji inline-block\" draggable=\"false\" height=\"24\" src=\"https://stat100.ameba.jp/blog/ucs/img/char/char3/212.png\" style=\"aspect-ratio: auto 24 / 24;\" width=\"24\"/><noscript><img alt=\"生ビール\" class=\"emoji inline-block\" draggable=\"false\" height=\"24\" src=\"https://stat100.ameba.jp/blog/ucs/img/char/char3/212.png\" width=\"24\"/></noscript>新しい仲間がいらっしゃいました<img alt=\"爆　　笑\" class=\"emoji inline-block\" draggable=\"false\" height=\"24\" src=\"https://stat100.ameba.jp/blog/ucs/img/char/char3/001.png\" style=\"aspect-ratio: auto 24 / 24;\" width=\"24\"/><noscript><img alt=\"爆　　笑\" class=\"emoji inline-block\" draggable=\"false\" height=\"24\" src=\"https://stat100.ameba.jp/blog/ucs/img/char/char3/001.png\" width=\"24\"/></noscript>ザオシャンハオ！</p><p>PCは幅広だから全部一行だっけど、スマホは小さいから全部2行だったわｗ</p><p>いらっしゃいませー<img alt=\"照れ\" class=\"emoji inline-block\" draggable=\"false\" height=\"24\" src=\"https://stat100.ameba.jp/blog/ucs/img/char/char3/007.png\" style=\"aspect-ratio: auto 24 / 24;\" width=\"24\"/><noscript><img alt=\"照れ\" class=\"emoji inline-block\" draggable=\"false\" height=\"24\" src=\"https://stat100.ameba.jp/blog/ucs/img/char/char3/007.png\" width=\"24\"/></noscript>BEER？なんて酒場にぴったりな名前なのかしら<img alt=\"生ビール\" class=\"emoji inline-block\" draggable=\"false\" height=\"24\" src=\"https://stat100.ameba.jp/blog/ucs/img/char/char3/212.png\" style=\"aspect-ratio: auto 24 / 24;\" width=\"24\"/><noscript><img alt=\"生ビール\" class=\"emoji inline-block\" draggable=\"false\" height=\"24\" src=\"https://stat100.ameba.jp/blog/ucs/img/char/char3/212.png\" width=\"24\"/></noscript></p><p>いらっしゃいませー<img alt=\"ニコニコ\" class=\"emoji inline-block\" draggable=\"false\" height=\"24\" src=\"https://stat100.ameba.jp/blog/ucs/img/char/char4/590.png\" style=\"aspect-ratio: auto 24 / 24;\" width=\"24\"/><noscript><img alt=\"ニコニコ\" class=\"emoji inline-block\" draggable=\"false\" height=\"24\" src=\"https://stat100.ameba.jp/blog/ucs/img/char/char4/590.png\" width=\"24\"/></noscript>いっぱい人が来るわー(ﾟДﾟ;)たまたま休暇を取ってたので誘導は任せて―</p>"
    },
    {
      "title": "酒場の掲示板　過去記事の修正連絡　2杯目",
      "url": "https://ameblo.jp/luidasbar/entry-12941382781.html",
      "content": "<p>いらっしゃいませ<img alt=\"照れ\" class=\"emoji inline-block\" draggable=\"false\" height=\"24\" src=\"https://stat100.ameba.jp/blog/ucs/img/char/char3/007.png\" style=\"aspect-ratio: auto 24 / 24;\" width=\"24\"/><noscript><img alt=\"照れ\" class=\"emoji inline-block\" draggable=\"false\" height=\"24\" src=\"https://stat100.ameba.jp/blog/ucs/img/char/char3/007.png\" width=\"24\"/></noscript></p><p>本日の更新は、過去記事の修正連絡 2杯目になります<img alt=\"アセアセ\" class=\"emoji inline-block\" draggable=\"false\" height=\"24\" src=\"https://stat100.ameba.jp/blog/ucs/img/char/char3/100.png\" style=\"aspect-ratio: auto 24 / 24;\" width=\"24\"/><noscript><img alt=\"アセアセ\" class=\"emoji inline-block\" draggable=\"false\" height=\"24\" src=\"https://stat100.ameba.jp/blog/ucs/img/char/char3/100.png\" width=\"24\"/></noscript></p><p>ブログもお陰様で1年以上運営させていただいています<img alt=\"照れ\" class=\"emoji inline-block\" draggable=\"false\" height=\"24\" src=\"https://stat100.ameba.jp/blog/ucs/img/char/char3/007.png\" style=\"aspect-ratio: auto 24 / 24;\" width=\"24\"/><noscript><img alt=\"照れ\" class=\"emoji inline-block\" draggable=\"false\" height=\"24\" src=\"https://stat100.ameba.jp/blog/ucs/img/char/char3/007.png\" width=\"24\"/></noscript></p><p>…が更新していく中で、過去にあげたものが古い情報となっていることがあり、指摘される事などもあります…<img alt=\"不安\" class=\"emoji inline-block\" draggable=\"false\" height=\"24\" src=\"https://stat100.ameba.jp/blog/ucs/img/char/char4/597.png\" style=\"aspect-ratio: auto 24 / 24;\" width=\"24\"/><noscript><img alt=\"不安\" class=\"emoji inline-block\" draggable=\"false\" height=\"24\" src=\"https://stat100.ameba.jp/blog/ucs/img/char/char4/597.png\" width=\"24\"/></noscript>随時修正を行い報告させて頂いていましたが、前の記事がブログの文字数制限60000に引っかかり更新できなくなりました<img alt=\"悲しい\" class=\"emoji inline-block\" draggable=\"false\" height=\"24\" src=\"https://stat100.ameba.jp/blog/ucs/img/char/char4/596.png\" style=\"aspect-ratio: auto 24 / 24;\" width=\"24\"/><noscript><img alt=\"悲しい\" class=\"emoji inline-block\" draggable=\"false\" height=\"24\" src=\"https://stat100.ameba.jp/blog/ucs/img/char/char4/596.png\" width=\"24\"/></noscript></p>"
    },
    {
      "title": "【RyD】20260214からの座席表",
      "url": "https://ameblo.jp/luidasbar/entry-12956551171.html",
      "content": "<p>※ルイーダの酒場内の業務連絡となります。</p><ul>\n<li>2026年2月14日の鯖内王城明けから使用予定の新しい座席表です。</li>\n<li>新しい座席表ではアンケートを基準とした熊狩行動開催時間毎でのグルーピングになります。</li>\n<li>今回は「チャレンジ席」「ゲスト席」などを設けておりません<img alt=\"アセアセ\" class=\"emoji inline-block\" draggable=\"false\" height=\"24\" src=\"https://stat100.ameba.jp/blog/ucs/img/char/char3/100.png\" style=\"aspect-ratio: auto 24 / 24;\" width=\"24\"/><noscript><img alt=\"アセアセ\" class=\"emoji inline-block\" draggable=\"false\" height=\"24\" src=\"https://stat100.ameba.jp/blog/ucs/img/char/char3/100.png\" width=\"24\"/></noscript></li>\n<li>基本的には2026年2月6日 9時段階の総力を元にしています。</li>\n<li>座席表は予定図です。突発的な原因で内容に修正が加わることがあります。</li>\n<li>時間訳で不都合など生じましたら担当に連絡ください。</li>\n</ul><div>並行</div><div>斜め</div>"
    }
  ]
}