{
  "articles": [
    {
      "title": "近況報告　10月23日～24日　「SIMAは未来からやってきた」",
      "url": "https://ameblo.jp/luidasbar/entry-12941344639.html",
      "content": "<p>あら…ハロたんやましいことでもあるのかしら？<img alt=\"ニヤリ\" class=\"emoji inline-block\" draggable=\"false\" height=\"24\" src=\"https://stat100.ameba.jp/blog/ucs/img/char/char3/012.png\" style=\"aspect-ratio: auto 24 / 24;\" width=\"24\"/><noscript><img alt=\"ニヤリ\" class=\"emoji inline-block\" draggable=\"false\" height=\"24\" src=\"https://stat100.ameba.jp/blog/ucs/img/char/char3/012.png\" width=\"24\"/></noscript></p><p>え？SIMAさん未来から来たの？<img alt=\"キョロキョロ\" class=\"emoji inline-block\" draggable=\"false\" height=\"24\" src=\"https://stat100.ameba.jp/blog/ucs/img/char/char3/016.png\" style=\"aspect-ratio: auto 24 / 24;\" width=\"24\"/><noscript><img alt=\"キョロキョロ\" class=\"emoji inline-block\" draggable=\"false\" height=\"24\" src=\"https://stat100.ameba.jp/blog/ucs/img/char/char3/016.png\" width=\"24\"/></noscript></p><p>出たな！って…人を化け物か何かの様に…あ、今ゾンべにだったわｗ</p><p>お望み通り題名にしてあげたわよ<img alt=\"キョロキョロ\" class=\"emoji inline-block\" draggable=\"false\" height=\"24\" src=\"https://stat100.ameba.jp/blog/ucs/img/char/char3/016.png\" style=\"aspect-ratio: auto 24 / 24;\" width=\"24\"/><noscript><img alt=\"キョロキョロ\" class=\"emoji inline-block\" draggable=\"false\" height=\"24\" src=\"https://stat100.ameba.jp/blog/ucs/img/char/char3/016.png\" width=\"24\"/></noscript>ついでにハッシュタグもねｗ</p>"
    },
    {
      "title": "酒場の掲示板　過去記事の修正連絡 2杯目",
      "url": "https://ameblo.jp/luidasbar/entry-12941382781.html",
      "content": "<p>いらっしゃいませ<img alt=\"照れ\" class=\"emoji inline-block\" draggable=\"false\" height=\"24\" src=\"https://stat100.ameba.jp/blog/ucs/img/char/char3/007.png\" style=\"aspect-ratio: auto 24 / 24;\" width=\"24\"/><noscript><img alt=\"照れ\" class=\"emoji inline-block\" draggable=\"false\" height=\"24\" src=\"https://stat100.ameba.jp/blog/ucs/img/char/char3/007.png\" width=\"24\"/></noscript></p><p>本日の更新は、過去記事の修正連絡 2杯目になります<img alt=\"アセアセ\" class=\"emoji inline-block\" draggable=\"false\" height=\"24\" src=\"https://stat100.ameba.jp/blog/ucs/img/char/char3/100.png\" style=\"aspect-ratio: auto 24 / 24;\" width=\"24\"/><noscript><img alt=\"アセアセ\" class=\"emoji inline-block\" draggable=\"false\" height=\"24\" src=\"https://stat100.ameba.jp/blog/ucs/img/char/char3/100.png\" width=\"24\"/></noscript></p><p>ブログもお陰様で1年以上運営させていただいています<img alt=\"照れ\" class=\"emoji inline-block\" draggable=\"false\" height=\"24\" src=\"https://stat100.ameba.jp/blog/ucs/img/char/char3/007.png\" style=\"aspect-ratio: auto 24 / 24;\" width=\"24\"/><noscript><img alt=\"照れ\" class=\"emoji inline-block\" draggable=\"false\" height=\"24\" src=\"https://stat100.ameba.jp/blog/ucs/img/char/char3/007.png\" width=\"24\"/></noscript></p><p>…が更新していく中で、過去にあげたものが古い情報となっていることがあり、指摘される事などもあります…<img alt=\"不安\" class=\"emoji inline-block\" draggable=\"false\" height=\"24\" src=\"https://stat100.ameba.jp/blog/ucs/img/char/char4/597.png\" style=\"aspect-ratio: auto 24 / 24;\" width=\"24\"/><noscript><img alt=\"不安\" class=\"emoji inline-block\" draggable=\"false\" height=\"24\" src=\"https://stat100.ameba.jp/blog/ucs/img/char/char4/597.png\" width=\"24\"/></noscript>随時修正を行い報告させて頂いていましたが、前の記事がブログの文字数制限60000に引っかかり更新できなくなりました<img alt=\"悲しい\" class=\"emoji inline-block\" draggable=\"false\" height=\"24\" src=\"https://stat100.ameba.jp/blog/ucs/img/char/char4/596.png\" style=\"aspect-ratio: auto 24 / 24;\" width=\"24\"/><noscript><img alt=\"悲しい\" class=\"emoji inline-block\" draggable=\"false\" height=\"24\" src=\"https://stat100.ameba.jp/blog/ucs/img/char/char4/596.png\" width=\"24\"/></noscript></p>"
    },
    {
      "title": "近況報告　10月20日～22日　※くさったSIMA更新ｗ　＋　後日画像追加(汗)",
      "url": "https://ameblo.jp/luidasbar/entry-12940831275.html",
      "content": "<p>HARUさん、おめでとうございますー<img alt=\"拍手\" class=\"emoji inline-block\" draggable=\"false\" height=\"24\" src=\"https://stat100.ameba.jp/blog/ucs/img/char/char3/130.png\" style=\"aspect-ratio: auto 24 / 24;\" width=\"24\"/><noscript><img alt=\"拍手\" class=\"emoji inline-block\" draggable=\"false\" height=\"24\" src=\"https://stat100.ameba.jp/blog/ucs/img/char/char3/130.png\" width=\"24\"/></noscript></p><p>SIMAさん、盛大な滑りおめでとうございますー_( ┐ﾉε:)ﾉｽﾞｺｰｗ</p><p>10/21は全国的に寒かったですねー…🥶寒くて寒くて顔色がこんなに悪くなりました<img alt=\"ゲロー\" class=\"emoji inline-block\" draggable=\"false\" height=\"24\" src=\"https://stat100.ameba.jp/blog/ucs/img/char/char3/038.png\" style=\"aspect-ratio: auto 24 / 24;\" width=\"24\"/><noscript><img alt=\"ゲロー\" class=\"emoji inline-block\" draggable=\"false\" height=\"24\" src=\"https://stat100.ameba.jp/blog/ucs/img/char/char3/038.png\" width=\"24\"/></noscript>ｗ</p><p>燃霜おめでとうございますー<img alt=\"拍手\" class=\"emoji inline-block\" draggable=\"false\" height=\"24\" src=\"https://stat100.ameba.jp/blog/ucs/img/char/char3/130.png\" style=\"aspect-ratio: auto 24 / 24;\" width=\"24\"/><noscript><img alt=\"拍手\" class=\"emoji inline-block\" draggable=\"false\" height=\"24\" src=\"https://stat100.ameba.jp/blog/ucs/img/char/char3/130.png\" width=\"24\"/></noscript></p>"
    }
  ]
}