{
  "articles": [
    {
      "title": "英雄セリフ研究所　専門家",
      "url": "https://ameblo.jp/luidasbar/entry-12940573044.html",
      "content": "<p><b style=\"font-weight:bold;\">※企画の特性上、音源が聴けるタイミングでの動画視聴をオススメします</b><img alt=\"口笛\" class=\"emoji inline-block\" draggable=\"false\" height=\"24\" src=\"https://stat100.ameba.jp/blog/ucs/img/char/char3/010.png\" style=\"aspect-ratio: auto 24 / 24;\" width=\"24\"/><noscript><img alt=\"口笛\" class=\"emoji inline-block\" draggable=\"false\" height=\"24\" src=\"https://stat100.ameba.jp/blog/ucs/img/char/char3/010.png\" width=\"24\"/></noscript></p><p>いらっしゃいませ<img alt=\"照れ\" class=\"emoji inline-block\" draggable=\"false\" height=\"24\" src=\"https://stat100.ameba.jp/blog/ucs/img/char/char3/007.png\" style=\"aspect-ratio: auto 24 / 24;\" width=\"24\"/><noscript><img alt=\"照れ\" class=\"emoji inline-block\" draggable=\"false\" height=\"24\" src=\"https://stat100.ameba.jp/blog/ucs/img/char/char3/007.png\" width=\"24\"/></noscript></p><p>本日は「英雄セリフ研究所　専門家」をご紹介<img alt=\"ウインク\" class=\"emoji inline-block\" draggable=\"false\" height=\"24\" src=\"https://stat100.ameba.jp/blog/ucs/img/char/char3/004.png\" style=\"aspect-ratio: auto 24 / 24;\" width=\"24\"/><noscript><img alt=\"ウインク\" class=\"emoji inline-block\" draggable=\"false\" height=\"24\" src=\"https://stat100.ameba.jp/blog/ucs/img/char/char3/004.png\" width=\"24\"/></noscript></p><p>ついに来たわー<img alt=\"照れ\" class=\"emoji inline-block\" draggable=\"false\" height=\"24\" src=\"https://stat100.ameba.jp/blog/ucs/img/char/char3/007.png\" style=\"aspect-ratio: auto 24 / 24;\" width=\"24\"/><noscript><img alt=\"照れ\" class=\"emoji inline-block\" draggable=\"false\" height=\"24\" src=\"https://stat100.ameba.jp/blog/ucs/img/char/char3/007.png\" width=\"24\"/></noscript>待ってたわー<img alt=\"ラブラブ\" class=\"emoji inline-block\" draggable=\"false\" height=\"24\" src=\"https://stat100.ameba.jp/blog/ucs/img/char/char3/084.png\" style=\"aspect-ratio: auto 24 / 24;\" width=\"24\"/><noscript><img alt=\"ラブラブ\" class=\"emoji inline-block\" draggable=\"false\" height=\"24\" src=\"https://stat100.ameba.jp/blog/ucs/img/char/char3/084.png\" width=\"24\"/></noscript>専門家の音声<img alt=\"キラキラ\" class=\"emoji inline-block\" draggable=\"false\" height=\"24\" src=\"https://stat100.ameba.jp/blog/ucs/img/char/char3/088.png\" style=\"aspect-ratio: auto 24 / 24;\" width=\"24\"/><noscript><img alt=\"キラキラ\" class=\"emoji inline-block\" draggable=\"false\" height=\"24\" src=\"https://stat100.ameba.jp/blog/ucs/img/char/char3/088.png\" width=\"24\"/></noscript></p>"
    },
    {
      "title": "20251022アプデ情報瓦版",
      "url": "https://ameblo.jp/luidasbar/entry-12940170639.html",
      "content": "<p>いらっしゃいませ<img alt=\"照れ\" class=\"emoji inline-block\" draggable=\"false\" height=\"24\" src=\"https://stat100.ameba.jp/blog/ucs/img/char/char3/007.png\" style=\"aspect-ratio: auto 24 / 24;\" width=\"24\"/><noscript><img alt=\"照れ\" class=\"emoji inline-block\" draggable=\"false\" height=\"24\" src=\"https://stat100.ameba.jp/blog/ucs/img/char/char3/007.png\" width=\"24\"/></noscript></p><p>本日は先日のアップデートでの更新情報を可能なものは画像付きでお届けするアプデ情報瓦版ですよー<img alt=\"爆　　笑\" class=\"emoji inline-block\" draggable=\"false\" height=\"24\" src=\"https://stat100.ameba.jp/blog/ucs/img/char/char3/001.png\" style=\"aspect-ratio: auto 24 / 24;\" width=\"24\"/><noscript><img alt=\"爆　　笑\" class=\"emoji inline-block\" draggable=\"false\" height=\"24\" src=\"https://stat100.ameba.jp/blog/ucs/img/char/char3/001.png\" width=\"24\"/></noscript></p><p style=\"text-align: center;\">------------------------------<br/>\n</p><p style=\"text-align: center;\"><b>2025年10月22日アップデート情報</b></p>"
    },
    {
      "title": "近況報告　10月18日～19日",
      "url": "https://ameblo.jp/luidasbar/entry-12939987422.html",
      "content": "<p>のんのさんおめでとうですー</p><p>貴重映像！あおべにの朝のリマインダー＆報酬分配ｗ　最後にやったのは…いつだったかしら<img alt=\"キョロキョロ\" class=\"emoji inline-block\" draggable=\"false\" height=\"24\" src=\"https://stat100.ameba.jp/blog/ucs/img/char/char3/016.png\" style=\"aspect-ratio: auto 24 / 24;\" width=\"24\"/><noscript><img alt=\"キョロキョロ\" class=\"emoji inline-block\" draggable=\"false\" height=\"24\" src=\"https://stat100.ameba.jp/blog/ucs/img/char/char3/016.png\" width=\"24\"/></noscript>ｗ</p><p>同盟通知も予約機能でお手軽に<img alt=\"びっくり\" class=\"emoji inline-block\" draggable=\"false\" height=\"24\" src=\"https://stat100.ameba.jp/blog/ucs/img/char/char3/014.png\" style=\"aspect-ratio: auto 24 / 24;\" width=\"24\"/><noscript><img alt=\"びっくり\" class=\"emoji inline-block\" draggable=\"false\" height=\"24\" src=\"https://stat100.ameba.jp/blog/ucs/img/char/char3/014.png\" width=\"24\"/></noscript>報酬分配もスライダーで簡単に<img alt=\"びっくり\" class=\"emoji inline-block\" draggable=\"false\" height=\"24\" src=\"https://stat100.ameba.jp/blog/ucs/img/char/char3/014.png\" style=\"aspect-ratio: auto 24 / 24;\" width=\"24\"/><noscript><img alt=\"びっくり\" class=\"emoji inline-block\" draggable=\"false\" height=\"24\" src=\"https://stat100.ameba.jp/blog/ucs/img/char/char3/014.png\" width=\"24\"/></noscript>便利な時代になったのぉー<img alt=\"ネガティブ\" class=\"emoji inline-block\" draggable=\"false\" height=\"24\" src=\"https://stat100.ameba.jp/blog/ucs/img/char/char4/625.png\" style=\"aspect-ratio: auto 24 / 24;\" width=\"24\"/><noscript><img alt=\"ネガティブ\" class=\"emoji inline-block\" draggable=\"false\" height=\"24\" src=\"https://stat100.ameba.jp/blog/ucs/img/char/char4/625.png\" width=\"24\"/></noscript>ｗｗｗ</p><p>SIMAさん、毎週毎朝ありがとうございます</p>"
    }
  ]
}